memcache/__init__.py
memcache/async_memcache.py
memcache/errors.py
memcache/memcache.py
memcache/meta_command.py
memcache/py.typed
memcache/serialize.py
memcache-0.14.0.dist-info/METADATA
memcache-0.14.0.dist-info/WHEEL
memcache-0.14.0.dist-info/licenses/LICENSE
memcache-0.14.0.dist-info/RECORD
