Metadata-Version: 2.4
Name: memcache
Version: 0.14.0
Summary: Memcached client for Python
Author-email: AN Long <aisk1988@gmail.com>
License-File: LICENSE
Requires-Python: >=3.7
Requires-Dist: anyio<4.0.0,>=3.0.0
Requires-Dist: hashring<2,>=1.5.1
